pl_bolts/__init__.py
pl_bolts/info.py
pl_bolts/setup_tools.py
pl_bolts/callbacks/__init__.py
pl_bolts/callbacks/byol_updates.py
pl_bolts/callbacks/data_monitor.py
pl_bolts/callbacks/knn_online.py
pl_bolts/callbacks/printing.py
pl_bolts/callbacks/ssl_online.py
pl_bolts/callbacks/variational.py
pl_bolts/callbacks/verification/__init__.py
pl_bolts/callbacks/verification/base.py
pl_bolts/callbacks/verification/batch_gradient.py
pl_bolts/callbacks/vision/__init__.py
pl_bolts/callbacks/vision/confused_logit.py
pl_bolts/callbacks/vision/image_generation.py
pl_bolts/datamodules/__init__.py
pl_bolts/datamodules/async_dataloader.py
pl_bolts/datamodules/binary_mnist_datamodule.py
pl_bolts/datamodules/cifar10_datamodule.py
pl_bolts/datamodules/cityscapes_datamodule.py
pl_bolts/datamodules/experience_source.py
pl_bolts/datamodules/fashion_mnist_datamodule.py
pl_bolts/datamodules/imagenet_datamodule.py
pl_bolts/datamodules/kitti_datamodule.py
pl_bolts/datamodules/mnist_datamodule.py
pl_bolts/datamodules/sklearn_datamodule.py
pl_bolts/datamodules/ssl_imagenet_datamodule.py
pl_bolts/datamodules/stl10_datamodule.py
pl_bolts/datamodules/vision_datamodule.py
pl_bolts/datamodules/vocdetection_datamodule.py
pl_bolts/datasets/__init__.py
pl_bolts/datasets/base_dataset.py
pl_bolts/datasets/cifar10_dataset.py
pl_bolts/datasets/concat_dataset.py
pl_bolts/datasets/dummy_dataset.py
pl_bolts/datasets/imagenet_dataset.py
pl_bolts/datasets/kitti_dataset.py
pl_bolts/datasets/mnist_dataset.py
pl_bolts/datasets/ssl_amdim_datasets.py
pl_bolts/losses/__init__.py
pl_bolts/losses/object_detection.py
pl_bolts/losses/rl.py
pl_bolts/losses/self_supervised_learning.py
pl_bolts/metrics/__init__.py
pl_bolts/metrics/aggregation.py
pl_bolts/metrics/object_detection.py
pl_bolts/models/__init__.py
pl_bolts/models/mnist_module.py
pl_bolts/models/autoencoders/__init__.py
pl_bolts/models/autoencoders/components.py
pl_bolts/models/autoencoders/basic_ae/__init__.py
pytorch_lightning_bolts-0.3.2.post1.dist-info/LICENSE
pytorch_lightning_bolts-0.3.2.post1.dist-info/METADATA
pytorch_lightning_bolts-0.3.2.post1.dist-info/WHEEL
pytorch_lightning_bolts-0.3.2.post1.dist-info/top_level.txt
pytorch_lightning_bolts-0.3.2.post1.dist-info/RECORD
