Metadata-Version: 2.1
Name: pytorch-lightning-bolts
Version: 0.3.2.post1
Summary: Deprecated in favor of Lightning Bolts - https://pypi.org/project/lightning-bolts
Home-page: https://github.com/PyTorchLightning/lightning-bolts
Author: PyTorchLightning et al.
Author-email: name@pytorchlightning.ai
License: Apache-2.0
Download-URL: https://github.com/PyTorchLightning/lightning-bolts
Project-URL: Bug Tracker, https://github.com/PyTorchLightning/lightning-bolts/issues
Project-URL: Documentation, https://lightning-bolts.rtfd.io/en/latest/
Project-URL: Source Code, https://github.com/PyTorchLightning/lightning-bolts
Keywords: deep learning,pytorch,AI
Platform: UNKNOWN
Classifier: Environment :: Console
Classifier: Natural Language :: English
Classifier: Development Status :: 4 - Beta
Classifier: Intended Audience :: Developers
Classifier: Topic :: Scientific/Engineering :: Artificial Intelligence
Classifier: Topic :: Scientific/Engineering :: Image Recognition
Classifier: Topic :: Scientific/Engineering :: Information Analysis
Classifier: License :: OSI Approved :: Apache Software License
Classifier: Operating System :: OS Independent
Classifier: Programming Language :: Python :: 3
Classifier: Programming Language :: Python :: 3.6
Classifier: Programming Language :: Python :: 3.7
Classifier: Programming Language :: Python :: 3.8
Requires-Python: >=3.6
Requires-Dist: pytorch-lightning (>=1.1.1)
Requires-Dist: torch (>=1.6)
Requires-Dist: torchmetrics (>=0.2.0)
Provides-Extra: dev
Requires-Dist: Pillow ; extra == 'dev'
Requires-Dist: atari-py (==0.2.6) ; extra == 'dev'
Requires-Dist: check-manifest ; extra == 'dev'
Requires-Dist: codecov (>=2.1) ; extra == 'dev'
Requires-Dist: flake8 ; extra == 'dev'
Requires-Dist: gym (>=0.17.2) ; extra == 'dev'
Requires-Dist: isort (>=5.6.4) ; extra == 'dev'
Requires-Dist: matplotlib ; extra == 'dev'
Requires-Dist: mypy (>=0.790) ; extra == 'dev'
Requires-Dist: opencv-python-headless ; extra == 'dev'
Requires-Dist: pre-commit (>=1.0) ; extra == 'dev'
Requires-Dist: pytest-cov (>2.10) ; extra == 'dev'
Requires-Dist: pytest (>=6.0) ; extra == 'dev'
Requires-Dist: scikit-learn (>=0.23) ; extra == 'dev'
Requires-Dist: scipy ; extra == 'dev'
Requires-Dist: torchvision (>=0.7) ; extra == 'dev'
Requires-Dist: twine (>=3.2) ; extra == 'dev'
Requires-Dist: wandb ; extra == 'dev'
Requires-Dist: yapf (>=0.29.0) ; extra == 'dev'
Provides-Extra: extra
Requires-Dist: Pillow ; extra == 'extra'
Requires-Dist: gym (>=0.17.2) ; extra == 'extra'
Requires-Dist: matplotlib ; extra == 'extra'
Requires-Dist: opencv-python-headless ; extra == 'extra'
Requires-Dist: scikit-learn (>=0.23) ; extra == 'extra'
Requires-Dist: scipy ; extra == 'extra'
Requires-Dist: torchvision (>=0.7) ; extra == 'extra'
Requires-Dist: wandb ; extra == 'extra'
Provides-Extra: loggers
Requires-Dist: matplotlib ; extra == 'loggers'
Requires-Dist: scipy ; extra == 'loggers'
Requires-Dist: wandb ; extra == 'loggers'
Provides-Extra: models
Requires-Dist: Pillow ; extra == 'models'
Requires-Dist: gym (>=0.17.2) ; extra == 'models'
Requires-Dist: opencv-python-headless ; extra == 'models'
Requires-Dist: scikit-learn (>=0.23) ; extra == 'models'
Requires-Dist: torchvision (>=0.7) ; extra == 'models'
Provides-Extra: test
Requires-Dist: atari-py (==0.2.6) ; extra == 'test'
Requires-Dist: check-manifest ; extra == 'test'
Requires-Dist: codecov (>=2.1) ; extra == 'test'
Requires-Dist: flake8 ; extra == 'test'
Requires-Dist: isort (>=5.6.4) ; extra == 'test'
Requires-Dist: mypy (>=0.790) ; extra == 'test'
Requires-Dist: pre-commit (>=1.0) ; extra == 'test'
Requires-Dist: pytest-cov (>2.10) ; extra == 'test'
Requires-Dist: pytest (>=6.0) ; extra == 'test'
Requires-Dist: scikit-learn (>=0.23) ; extra == 'test'
Requires-Dist: twine (>=3.2) ; extra == 'test'
Requires-Dist: yapf (>=0.29.0) ; extra == 'test'
